actelink/variables.py
actelink_variables-0.6.15.dist-info/LICENSE.txt
actelink_variables-0.6.15.dist-info/METADATA
actelink_variables-0.6.15.dist-info/WHEEL
actelink_variables-0.6.15.dist-info/top_level.txt
actelink_variables-0.6.15.dist-info/RECORD
