Metadata-Version: 2.1
Name: actelink-variables
Version: 0.6.15
Summary: Actelink helpers library for variables management
Author: Actelink
License: LICENSE.txt
Classifier: Programming Language :: Python
Classifier: Programming Language :: Python :: 3
Classifier: Programming Language :: Python :: 3.10
Classifier: License :: OSI Approved :: MIT License
Classifier: Operating System :: OS Independent
Requires-Python: >=3.6
License-File: LICENSE.txt
Requires-Dist: requests
Requires-Dist: actelink.computation
